Metadata-Version: 2.1
Name: badge
Version: 2019.3.22
Summary: badge generator
Home-page: https://github.com/looking-for-a-job/badge.py
License: UNKNOWN
Keywords: badge
Platform: UNKNOWN
Classifier: License :: Public Domain
Classifier: Operating System :: OS Independent
Classifier: Programming Language :: Python
Classifier: Programming Language :: Python :: 2
Classifier: Programming Language :: Python :: 2.7
Classifier: Programming Language :: Python :: 3
Classifier: Programming Language :: Python :: 3.4
Classifier: Programming Language :: Python :: 3.5
Classifier: Programming Language :: Python :: 3.6
Classifier: Programming Language :: Python :: 3.7
Classifier: Topic :: Software Development
Requires-Dist: format-keys
Requires-Dist: public
Requires-Dist: setuptools
